DSM/__init__.py
DSM/Ensemble/__init__.py
DSM/Ensemble/EMLR.py
DSM/metrics.py
DSM/models/__init__.py
DSM/models/BaseModel.py
DSM/models/DayFeaturesLR.py
DSM/models/DayFunctions.py
DSM/models/RLS.py
DSM/models/SDaysAVR.py
DSM/models/STA.py
DSM/models/TDaysAVR.py
DSM/structures/__init__.py
DSM/structures/dsm_timeseries.py
DSM/Utils.py
dsm_hse_perm_ru-0.2.dist-info/METADATA
dsm_hse_perm_ru-0.2.dist-info/WHEEL
dsm_hse_perm_ru-0.2.dist-info/RECORD
