Metadata-Version: 2.1
Name: DSM_hse_perm_ru
Version: 0.2
Summary: Библиотека прогнозных моделей DSM
Author: Your Name
Author-email: you@example.com
Requires-Python: >=3.10,<4.0
Classifier: Programming Language :: Python :: 3
Classifier: Programming Language :: Python :: 3.10
Classifier: Programming Language :: Python :: 3.11
Classifier: Programming Language :: Python :: 3.12
Provides-Extra: docs
Requires-Dist: Sphinx (==5.0) ; extra == "docs"
Requires-Dist: numpy (>=1.26.3,<2.0.0)
Requires-Dist: padasip (>=1.2.2,<2.0.0)
Requires-Dist: pandas (>=2.1.4,<3.0.0)
Requires-Dist: scikit-learn (>=1.3.2,<2.0.0)
Requires-Dist: sphinx-rtd-theme (==1.0.0) ; extra == "docs"
Requires-Dist: sphinxcontrib-napoleon (==0.7) ; extra == "docs"
Requires-Dist: tqdm (>=4.66.1,<5.0.0)
